<?xml version="1.0" encoding="utf-8"?>
<odoo>
    <data>
        <!-- sale.order form view -->
        <!-- oform (odoo form) -->
        <record id="booking_order_view_form" model="ir.ui.view">
            <field name="name">booking.order.form</field>
            <field name="model">sale.order</field>
            <field name="inherit_id" ref="sale.view_order_form"/>
            
            <field name="arch" type="xml">
                <xpath expr='//button[@name="action_confirm"]' position="after">
                    <button name="action_check" string="Check" class="btn-primary" type="object"/>
                </xpath>
                
                <xpath expr="//button[@name='action_view_invoice']" position="after">
                    <button type="action" name="%(action_view_wo)d"
                            class="oe_stat_button"
                            icon="fa-book" attrs="{'invisible': [('wo_count', '=', 0)]}">
                        <field name="wo_count" widget="statinfo" string="Work Order"/>
                    </button>
                </xpath>
                
                <field name="partner_id" position="after">
                    <field name="is_booking_order" invisible="1"/>
                    <field name="team" required="1" attrs="{'invisible': [('is_booking_order', '=', False)]}"/>
                    <field name="team_leader" required="1" attrs="{'invisible': [('is_booking_order', '=', False)]}"/>
                    <field name="team_members" widget="many2many_tags" required="1"
                           attrs="{'invisible': [('is_booking_order', '=', False)]}"/>
                </field>
                
                <field name="payment_term_id" position="after">
                    <field name="booking_start" required="1" attrs="{'invisible': [('is_booking_order', '=', False)]}"/>
                    <field name="booking_end" required="1" attrs="{'invisible': [('is_booking_order', '=', False)]}"/>
                </field>
            </field>
        </record>

        <!-- sale.order action window -->
        <!-- oact (odoo action) -->
        <record id="booking_order_action" model="ir.actions.act_window">
            <field name="name">Booking Order Action</field>
            <field name="res_model">sale.order</field>
            <field name="view_mode">tree,form</field>
            <field name="domain">[('is_booking_order', '=', 1)]</field>
            
            <field name="context">{
                'default_is_booking_order': 1
            }</field>
            
            <field name="help" type="html">
                <p class="oe_view_nocontent_create">
                    Klik untuk menambahkan
                </p>
                
                <p>Tekan tombol create untuk Booking Order baru</p>
            </field>
        </record>

        <menuitem 
            id="booking_order_menu_categ"
            name="Booking Order"
            parent="booking_main" 
            sequence="1" 
            action="booking_order_action"/>
    </data>
</odoo>